{
    "Allen R Pruittrown City": {
        "Apples - OH|CA": 8972156,
        "Cell phones - NC|OR": 9448326,
        "Light bulbs - MO|TX": 2540983,
        "Oranges - IA|IL": 3508825,
        "Recyclables - VA|FL": 4460003,
        "Wood - KY|LA": 3616632,
        "Wood - MN|IL": 4336890},
    "Arachus Incashville": {
        "Apples - OH|CA": 9034731,
        "Cell phones - NC|OR": 9549074,
        "Light bulbs - MO|TX": 4848784,
        "Oranges - IA|IL": 3076468,
        "Recyclables - VA|FL": 3432699,
        "Wood - KY|LA": 4201901,
        "Wood - MN|IL": 3694921},
    "Arrow Towing Llcent": {
        "Apples - OH|CA": 9145606,
        "Cell phones - NC|OR": 9623590,
        "Light bulbs - MO|TX": 4973339,
        "Oranges - IA|IL": 3150894,
        "Recyclables - VA|FL": 3539456,
        "Wood - KY|LA": 4326456,
        "Wood - MN|IL": 3719330},
    "Beyond Landscape & Design Llcilsonville": {
        "Apples - OH|CA": 7963114,
        "Cell phones - NC|OR": 9255524,
        "Light bulbs - MO|TX": 7051560,
        "Oranges - IA|IL": 6844094,
        "Recyclables - VA|FL": 10027932,
        "Wood - KY|LA": 8776415,
        "Wood - MN|IL": 7305309},
    "Como Construction Llcottstown": {
        "Apples - OH|CA": 9254284,
        "Cell phones - NC|OR": 9741817,
        "Light bulbs - MO|TX": 5100919,
        "Oranges - IA|IL": 3259572,
        "Recyclables - VA|FL": 3645216,
        "Wood - KY|LA": 4454035,
        "Wood - MN|IL": 3828008},
    "Dawna L Zanderppleton": {
        "Apples - OH|CA": 8580558,
        "Cell phones - NC|OR": 8819747,
        "Light bulbs - MO|TX": 7203001,
        "Oranges - IA|IL": 6219143,
        "Recyclables - VA|FL": 9852284,
        "Wood - KY|LA": 8728192,
        "Wood - MN|IL": 6176556},
    "Dupree Testing Services Incutchinson": {
        "Apples - OH|CA": 8825305,
        "Cell phones - NC|OR": 9430502,
        "Light bulbs - MO|TX": 2473927,
        "Oranges - IA|IL": 3471913,
        "Recyclables - VA|FL": 4504765,
        "Wood - KY|LA": 3534854,
        "Wood - MN|IL": 4269633},
    "Edmon'S Unique Furniture & Stone Gallery Inc.Os Angeles": {
        "Apples - OH|CA": 7716498,
        "Cell phones - NC|OR": 8668693,
        "Light bulbs - MO|TX": 3037115,
        "Oranges - IA|IL": 761035,
        "Recyclables - VA|FL": 4040890,
        "Wood - KY|LA": 3291925,
        "Wood - MN|IL": 1357465},
    "Efrain Morales Diazorwalk": {
        "Apples - OH|CA": 7886882,
        "Cell phones - NC|OR": 8511450,
        "Light bulbs - MO|TX": 2006079,
        "Oranges - IA|IL": 1443171,
        "Recyclables - VA|FL": 4180862,
        "Wood - KY|LA": 3230350,
        "Wood - MN|IL": 2392170},
    "Empire Of Dirt Llcquality": {
        "Apples - OH|CA": 10651124,
        "Cell phones - NC|OR": 11152204,
        "Light bulbs - MO|TX": 6533401,
        "Oranges - IA|IL": 4642298,
        "Recyclables - VA|FL": 5031517,
        "Wood - KY|LA": 5898955,
        "Wood - MN|IL": 5210733},
    "Filippo Lumaroallston": {
        "Apples - OH|CA": 8972156,
        "Cell phones - NC|OR": 9448326,
        "Light bulbs - MO|TX": 2540983,
        "Oranges - IA|IL": 3508825,
        "Recyclables - VA|FL": 4460003,
        "Wood - KY|LA": 3616632,
        "Wood - MN|IL": 4336890},
    "Fish-Bones Towingew York": {
        "Apples - OH|CA": 7811258,
        "Cell phones - NC|OR": 8763453,
        "Light bulbs - MO|TX": 3325263,
        "Oranges - IA|IL": 843462,
        "Recyclables - VA|FL": 4420370,
        "Wood - KY|LA": 3621880,
        "Wood - MN|IL": 1266261},
    "Gary Lee Wilcoxpencer": {
        "Apples - OH|CA": 8412803,
        "Cell phones - NC|OR": 9250538,
        "Light bulbs - MO|TX": 4090892,
        "Oranges - IA|IL": 1643152,
        "Recyclables - VA|FL": 5127840,
        "Wood - KY|LA": 4329350,
        "Wood - MN|IL": 1550926},
    "Hartford Plastics Incartford": {
        "Apples - OH|CA": 8283089,
        "Cell phones - NC|OR": 8699198,
        "Light bulbs - MO|TX": 2325952,
        "Oranges - IA|IL": 2070819,
        "Recyclables - VA|FL": 3053437,
        "Wood - KY|LA": 2600942,
        "Wood - MN|IL": 3020814},
    "High Pines Farm Llcontello": {
        "Apples - OH|CA": 7721469,
        "Cell phones - NC|OR": 8673664,
        "Light bulbs - MO|TX": 3075967,
        "Oranges - IA|IL": 850170,
        "Recyclables - VA|FL": 3995875,
        "Wood - KY|LA": 3265563,
        "Wood - MN|IL": 1330045},
    "I N H Relocation Services Incoodbridge": {
        "Apples - OH|CA": 8765597,
        "Cell phones - NC|OR": 9423502,
        "Light bulbs - MO|TX": 2774041,
        "Oranges - IA|IL": 3733378,
        "Recyclables - VA|FL": 5133782,
        "Wood - KY|LA": 4103649,
        "Wood - MN|IL": 4552654},
    "Ibrahim Chimandalpharetta": {
        "Apples - OH|CA": 7746386,
        "Cell phones - NC|OR": 8768583,
        "Light bulbs - MO|TX": 3613709,
        "Oranges - IA|IL": 1547117,
        "Recyclables - VA|FL": 3608953,
        "Wood - KY|LA": 3281198,
        "Wood - MN|IL": 2115554},
    "Jacques N Faucherochester": {
        "Apples - OH|CA": 7700452,
        "Cell phones - NC|OR": 8476511,
        "Light bulbs - MO|TX": 2421627,
        "Oranges - IA|IL": 1484018,
        "Recyclables - VA|FL": 4571531,
        "Wood - KY|LA": 3618130,
        "Wood - MN|IL": 2157281},
    "James Haas Al Haas Shelly Haasairfield": {
        "Apples - OH|CA": 9058872,
        "Cell phones - NC|OR": 9488202,
        "Light bulbs - MO|TX": 4704272,
        "Oranges - IA|IL": 3100610,
        "Recyclables - VA|FL": 3173155,
        "Wood - KY|LA": 4115750,
        "Wood - MN|IL": 3742760},
    "Jeffery Allan Luiacine": {
        "Apples - OH|CA": 8582240,
        "Cell phones - NC|OR": 8806382,
        "Light bulbs - MO|TX": 2486202,
        "Oranges - IA|IL": 2564139,
        "Recyclables - VA|FL": 2867580,
        "Wood - KY|LA": 2605584,
        "Wood - MN|IL": 3466078},
    "Jeffrey A Shepardypsum": {
        "Apples - OH|CA": 8542769,
        "Cell phones - NC|OR": 8544247,
        "Light bulbs - MO|TX": 2862537,
        "Oranges - IA|IL": 2406606,
        "Recyclables - VA|FL": 2523522,
        "Wood - KY|LA": 2740268,
        "Wood - MN|IL": 3308545},
    "Jevin Q Watsonillsboro": {
        "Apples - OH|CA": 8837185,
        "Cell phones - NC|OR": 8760355,
        "Light bulbs - MO|TX": 3043838,
        "Oranges - IA|IL": 2777874,
        "Recyclables - VA|FL": 2452733,
        "Wood - KY|LA": 2868374,
        "Wood - MN|IL": 3679813},
    "John Bianchiake Havasu City": {
        "Apples - OH|CA": 8890615,
        "Cell phones - NC|OR": 9262335,
        "Light bulbs - MO|TX": 7896735,
        "Oranges - IA|IL": 6626437,
        "Recyclables - VA|FL": 10403812,
        "Wood - KY|LA": 9294338,
        "Wood - MN|IL": 6625116},
    "Jorge L Denisollywood": {
        "Apples - OH|CA": 7880030,
        "Cell phones - NC|OR": 8723393,
        "Light bulbs - MO|TX": 4354522,
        "Oranges - IA|IL": 4030864,
        "Recyclables - VA|FL": 7138629,
        "Wood - KY|LA": 5895754,
        "Wood - MN|IL": 4559714},
    "Jwj Interests Incealy": {
        "Apples - OH|CA": 8907405,
        "Cell phones - NC|OR": 9319371,
        "Light bulbs - MO|TX": 4550334,
        "Oranges - IA|IL": 2949142,
        "Recyclables - VA|FL": 3013251,
        "Wood - KY|LA": 3961812,
        "Wood - MN|IL": 3591293},
    "Kjellberg'S Carpet Oneuffalo": {
        "Apples - OH|CA": 7747784,
        "Cell phones - NC|OR": 8745016,
        "Light bulbs - MO|TX": 3592607,
        "Oranges - IA|IL": 1788054,
        "Recyclables - VA|FL": 3256519,
        "Wood - KY|LA": 3141748,
        "Wood - MN|IL": 2401559},
    "Loren Martinrand Junction": {
        "Apples - OH|CA": 8709108,
        "Cell phones - NC|OR": 8992838,
        "Light bulbs - MO|TX": 7758961,
        "Oranges - IA|IL": 6837017,
        "Recyclables - VA|FL": 10408244,
        "Wood - KY|LA": 9284152,
        "Wood - MN|IL": 6946598},
    "Macomb Iron Llchesterfield": {
        "Apples - OH|CA": 7904344,
        "Cell phones - NC|OR": 8840763,
        "Light bulbs - MO|TX": 3881262,
        "Oranges - IA|IL": 1866150,
        "Recyclables - VA|FL": 3422404,
        "Wood - KY|LA": 3430403,
        "Wood - MN|IL": 2434586},
    "Martinez Transport Llcdaho Falls": {
        "Apples - OH|CA": 7721469,
        "Cell phones - NC|OR": 8673664,
        "Light bulbs - MO|TX": 3075967,
        "Oranges - IA|IL": 850170,
        "Recyclables - VA|FL": 3995875,
        "Wood - KY|LA": 3265563,
        "Wood - MN|IL": 1330045},
    "Michael J Geenenaukauna": {
        "Apples - OH|CA": 8142247,
        "Cell phones - NC|OR": 9014705,
        "Light bulbs - MO|TX": 2870473,
        "Oranges - IA|IL": 3543195,
        "Recyclables - VA|FL": 5683192,
        "Wood - KY|LA": 4585856,
        "Wood - MN|IL": 4269126},
    "Paul J Krez Companyorton Grove": {
        "Apples - OH|CA": 8815514,
        "Cell phones - NC|OR": 8508442,
        "Light bulbs - MO|TX": 3427862,
        "Oranges - IA|IL": 2847950,
        "Recyclables - VA|FL": 2349601,
        "Wood - KY|LA": 3048358,
        "Wood - MN|IL": 3614997},
    "Peet'S Tree Serviceinterport": {
        "Apples - OH|CA": 8756765,
        "Cell phones - NC|OR": 9416077,
        "Light bulbs - MO|TX": 2726076,
        "Oranges - IA|IL": 3685413,
        "Recyclables - VA|FL": 5089609,
        "Wood - KY|LA": 4058069,
        "Wood - MN|IL": 4504689},
    "Ramiro Castilloucson": {
        "Apples - OH|CA": 7708736,
        "Cell phones - NC|OR": 8438402,
        "Light bulbs - MO|TX": 5328795,
        "Oranges - IA|IL": 4406851,
        "Recyclables - VA|FL": 7978079,
        "Wood - KY|LA": 6853986,
        "Wood - MN|IL": 4831549},
    "Ricardo Juradoacramento": {
        "Apples - OH|CA": 8872981,
        "Cell phones - NC|OR": 8995378,
        "Light bulbs - MO|TX": 4096496,
        "Oranges - IA|IL": 2951779,
        "Recyclables - VA|FL": 2556852,
        "Wood - KY|LA": 3578001,
        "Wood - MN|IL": 3710240},
    "Robert Robertsonairhope": {
        "Apples - OH|CA": 8221089,
        "Cell phones - NC|OR": 9073071,
        "Light bulbs - MO|TX": 3721322,
        "Oranges - IA|IL": 1398996,
        "Recyclables - VA|FL": 4684092,
        "Wood - KY|LA": 3941431,
        "Wood - MN|IL": 1373803},
    "Rubye Hunterincolnton": {
        "Apples - OH|CA": 9236874,
        "Cell phones - NC|OR": 9751603,
        "Light bulbs - MO|TX": 5084162,
        "Oranges - IA|IL": 3295705,
        "Recyclables - VA|FL": 3579355,
        "Wood - KY|LA": 4437279,
        "Wood - MN|IL": 3864142},
    "Scott Cassidylanchardville": {
        "Apples - OH|CA": 7751073,
        "Cell phones - NC|OR": 8527133,
        "Light bulbs - MO|TX": 3760419,
        "Oranges - IA|IL": 3154092,
        "Recyclables - VA|FL": 6473873,
        "Wood - KY|LA": 5301651,
        "Wood - MN|IL": 3682941},
    "Sidhu Trucking Incarrisburg": {
        "Apples - OH|CA": 8357902,
        "Cell phones - NC|OR": 9062285,
        "Light bulbs - MO|TX": 1956090,
        "Oranges - IA|IL": 2810548,
        "Recyclables - VA|FL": 4305940,
        "Wood - KY|LA": 3336351,
        "Wood - MN|IL": 3608268},
    "Sullivans' Homestead Inclympia": {
        "Apples - OH|CA": 10611956,
        "Cell phones - NC|OR": 10460757,
        "Light bulbs - MO|TX": 4749963,
        "Oranges - IA|IL": 4692807,
        "Recyclables - VA|FL": 2824260,
        "Wood - KY|LA": 4377329,
        "Wood - MN|IL": 5594745},
    "Turenne Auto Body Llchorp": {
        "Apples - OH|CA": 8756765,
        "Cell phones - NC|OR": 9416077,
        "Light bulbs - MO|TX": 2726076,
        "Oranges - IA|IL": 3685413,
        "Recyclables - VA|FL": 5089609,
        "Wood - KY|LA": 4058069,
        "Wood - MN|IL": 4504689},
    "Viking Products Of Austin Incustin": {
        "Apples - OH|CA": 8057613,
        "Cell phones - NC|OR": 8467762,
        "Light bulbs - MO|TX": 2271594,
        "Oranges - IA|IL": 1724432,
        "Recyclables - VA|FL": 3051922,
        "Wood - KY|LA": 2713952,
        "Wood - MN|IL": 2674427},
    "Vincent Rodriguezansas City": {
        "Apples - OH|CA": 7941981,
        "Cell phones - NC|OR": 9008740,
        "Light bulbs - MO|TX": 4679154,
        "Oranges - IA|IL": 5095423,
        "Recyclables - VA|FL": 7535843,
        "Wood - KY|LA": 6415428,
        "Wood - MN|IL": 5768685},
    "Wayne E Bollinauvoo": {
        "Apples - OH|CA": 7716575,
        "Cell phones - NC|OR": 8446240,
        "Light bulbs - MO|TX": 5328995,
        "Oranges - IA|IL": 4407051,
        "Recyclables - VA|FL": 7978278,
        "Wood - KY|LA": 6854186,
        "Wood - MN|IL": 4831749},
    "Wisebuys Stores Incouverneur": {
        "Apples - OH|CA": 8010012,
        "Cell phones - NC|OR": 8717603,
        "Light bulbs - MO|TX": 3612299,
        "Oranges - IA|IL": 2079560,
        "Recyclables - VA|FL": 2861147,
        "Wood - KY|LA": 3197120,
        "Wood - MN|IL": 2838022}
}

